Athene/__init__.py
Athene-0.0.1.dist-info/LICENSE
Athene-0.0.1.dist-info/METADATA
Athene-0.0.1.dist-info/WHEEL
Athene-0.0.1.dist-info/top_level.txt
Athene-0.0.1.dist-info/RECORD
