Metadata-Version: 2.1
Name: Athene
Version: 0.0.1
Summary: ATHENE: THE NLP Engine
Home-page: https://github.com/lvzii/Athene
Author: youshuJi
Author-email: zjs20001205@gmail.com
License: UNKNOWN
Project-URL: Bug Tracker, https://github.com/lvzii/Athene/issues
Platform: UNKNOWN
Classifier: Programming Language :: Python :: 3
Classifier: License :: OSI Approved :: MIT License
Classifier: Operating System :: OS Independent
Requires-Python: >=3.6
License-File: LICENSE
